setup.py
pulumi_std/__init__.py
pulumi_std/_utilities.py
pulumi_std/abs.py
pulumi_std/abspath.py
pulumi_std/alltrue.py
pulumi_std/anytrue.py
pulumi_std/base64decode.py
pulumi_std/base64encode.py
pulumi_std/base64gzip.py
pulumi_std/base64sha256.py
pulumi_std/base64sha512.py
pulumi_std/basename.py
pulumi_std/bcrypt.py
pulumi_std/ceil.py
pulumi_std/chomp.py
pulumi_std/chunklist.py
pulumi_std/cidrhost.py
pulumi_std/cidrnetmask.py
pulumi_std/cidrsubnet.py
pulumi_std/coalesce.py
pulumi_std/coalescelist.py
pulumi_std/compact.py
pulumi_std/concat.py
pulumi_std/contains.py
pulumi_std/csvdecode.py
pulumi_std/dirname.py
pulumi_std/distinct.py
pulumi_std/element.py
pulumi_std/endswith.py
pulumi_std/file.py
pulumi_std/filebase64.py
pulumi_std/filebase64sha256.py
pulumi_std/filebase64sha512.py
pulumi_std/fileexists.py
pulumi_std/filemd5.py
pulumi_std/filesha1.py
pulumi_std/filesha256.py
pulumi_std/filesha512.py
pulumi_std/flatten.py
pulumi_std/floor.py
pulumi_std/format.py
pulumi_std/indent.py
pulumi_std/index.py
pulumi_std/join.py
pulumi_std/jsondecode.py
pulumi_std/jsonencode.py
pulumi_std/keys.py
pulumi_std/length.py
pulumi_std/log.py
pulumi_std/lookup.py
pulumi_std/lower.py
pulumi_std/map.py
pulumi_std/matchkeys.py
pulumi_std/max.py
pulumi_std/md5.py
pulumi_std/merge.py
pulumi_std/min.py
pulumi_std/parseint.py
pulumi_std/pathexpand.py
pulumi_std/pow.py
pulumi_std/provider.py
pulumi_std/pulumi-plugin.json
pulumi_std/py.typed
pulumi_std/range.py
pulumi_std/replace.py
pulumi_std/reverse.py
pulumi_std/rsadecrypt.py
pulumi_std/sha1.py
pulumi_std/sha256.py
pulumi_std/sha512.py
pulumi_std/signum.py
pulumi_std/slice.py
pulumi_std/sort.py
pulumi_std/split.py
pulumi_std/startswith.py
pulumi_std/strrev.py
pulumi_std/substr.py
pulumi_std/sum.py
pulumi_std/timeadd.py
pulumi_std/timecmp.py
pulumi_std/timestamp.py
pulumi_std/title.py
pulumi_std/tobool.py
pulumi_std/tolist.py
pulumi_std/tonumber.py
pulumi_std/toset.py
pulumi_std/tostring.py
pulumi_std/transpose.py
pulumi_std/trim.py
pulumi_std.egg-info/PKG-INFO
pulumi_std.egg-info/SOURCES.txt
pulumi_std.egg-info/dependency_links.txt
pulumi_std.egg-info/not-zip-safe
pulumi_std.egg-info/requires.txt
pulumi_std.egg-info/top_level.txt