Metadata-Version: 2.1
Name: pulumi-std
Version: 1.7.3
Summary: Standard library functions
Home-page: https://github.com/pulumi/pulumi-std
Project-URL: Repository, https://github.com/pulumi/pulumi-std
Requires-Python: >=3.8
